distributions/__init__.py
distributions/distribution.py
distributions/example.py
distributions/gaussian.py
distributions/numbers.txt
Guassian_Test_Package-1.0.dist-info/LICENCE
Guassian_Test_Package-1.0.dist-info/METADATA
Guassian_Test_Package-1.0.dist-info/WHEEL
Guassian_Test_Package-1.0.dist-info/top_level.txt
Guassian_Test_Package-1.0.dist-info/RECORD
