Metadata-Version: 2.1
Name: Guassian-Test-Package
Version: 1.0
Summary: Nakul Python Gaussian Test Package
Home-page: https://www.github.com/Nakulbajaj101/gaussian-test-package
Author: Nakul Bajaj
Author-email: bajaj.nakul@gmail.om
License: MIT
Platform: UNKNOWN
Classifier: License :: OSI Approved :: MIT License
Classifier: Programming Language :: Python :: 3
Classifier: Programming Language :: Python :: 3.6
Classifier: Programming Language :: Python :: 3.7
Classifier: Programming Language :: Python :: 3.8
Requires-Python: >=3.8
License-File: LICENCE
Requires-Dist: cycler (==0.10.0)
Requires-Dist: flake8 (==3.9.2)
Requires-Dist: kiwisolver (==1.3.2)
Requires-Dist: matplotlib (==3.4.3)
Requires-Dist: mccabe (==0.6.1)
Requires-Dist: numpy (==1.21.2)
Requires-Dist: Pillow (==8.3.2)
Requires-Dist: pycodestyle (==2.7.0)
Requires-Dist: pyflakes (==2.3.1)
Requires-Dist: pyparsing (==2.4.7)
Requires-Dist: python-dateutil (==2.8.2)
Requires-Dist: six (==1.16.0)
